manolyamailsender/MailMan.py
manolyamailsender/__init__.py
manolyamailsender/test.py
manolyamailsender-0.0.2.dist-info/LICENSE
manolyamailsender-0.0.2.dist-info/METADATA
manolyamailsender-0.0.2.dist-info/WHEEL
manolyamailsender-0.0.2.dist-info/top_level.txt
manolyamailsender-0.0.2.dist-info/RECORD
