Metadata-Version: 2.1
Name: manolyamailsender
Version: 0.0.2
Summary: Simple mail sender
Home-page: https://github.com/realpython/reader
Author: Umut Ucok
Author-email: ucok.umut@gmail.com
License: MIT
Platform: UNKNOWN
Classifier: License :: OSI Approved :: MIT License
Classifier: Programming Language :: Python :: 3
Classifier: Programming Language :: Python :: 3.7
